[[{"topology": [{"type": "dense", "act": "relu", "units": 730}], "epoch": 7, "batch_size": 64, "loss": "mean_absolute_error", "opt": "nadam", "accuracy": 0.8399999737739563}, {"topology": [{"type": "dense", "act": "selu", "units": 378}, {"type": "dense", "act": "softmax", "units": 233}], "epoch": 5, "batch_size": 64, "loss": "categorical_crossentropy", "opt": "adagrad", "accuracy": 0.6549999713897705}, {"topology": [{"type": "dense", "act": "sigmoid", "units": 121}, {"type": "dense", "act": "linear", "units": 191}], "epoch": 7, "batch_size": 64, "loss": "binary_crossentropy", "opt": "nadam", "accuracy": 0.9575000405311584}, {"topology": [{"type": "dense", "act": "linear", "units": 498}], "epoch": 4, "batch_size": 64, "loss": "sparse_categorical_crossentropy", "opt": "adamax", "accuracy": 0}, {"topology": [{"type": "dense", "act": "sigmoid", "units": 231}], "epoch": 8, "batch_size": 64, "loss": "mean_squared_error", "opt": "adam", "accuracy": 0.7760000228881836}], [{"topology": [{"type": "dense", "act": "sigmoid", "units": 121}, {"type": "dense", "act": "linear", "units": 191}], "epoch": 7, "batch_size": 64, "loss": "binary_crossentropy", "opt": "nadam", "accuracy": 0.3384999930858612}, {"topology": [{"type": "dense", "act": "relu", "units": 730}], "epoch": 7, "batch_size": 64, "loss": "mean_absolute_error", "opt": "nadam", "accuracy": 0.8479999899864197}, {"topology": [{"type": "dense", "act": "sigmoid", "units": 121}, {"type": "dense", "act": "relu", "units": 730}], "epoch": 6, "batch_size": 64, "loss": "mean_absolute_error", "opt": "adamax", "accuracy": 0.6200000047683716}, {"topology": [{"type": "dense", "act": "linear", "units": 191}], "epoch": 6, "batch_size": 64, "loss": "mean_squared_error", "opt": "rmsprop", "accuracy": 0.5820000171661377}], [{"topology": [{"type": "dense", "act": "relu", "units": 730}], "epoch": 7, "batch_size": 64, "loss": "mean_absolute_error", "opt": "nadam", "accuracy": 0.8029999732971191}, {"topology": [{"type": "dense", "act": "relu", "units": 730}], "epoch": 6, "batch_size": 64, "loss": "binary_crossentropy", "opt": "adagrad", "accuracy": 0.9007000923156738}, {"topology": [{"type": "dense", "act": "relu", "units": 730}], "epoch": 6, "batch_size": 64, "loss": "sparse_categorical_crossentropy", "opt": "adadelta", "accuracy": 0}, {"topology": [{"type": "dense", "act": "relu", "units": 730}], "epoch": 6, "batch_size": 64, "loss": "sparse_categorical_crossentropy", "opt": "adagrad", "accuracy": 0}, {"topology": [{"type": "dense", "act": "relu", "units": 730}], "epoch": 6, "batch_size": 64, "loss": "mean_absolute_error", "opt": "adadelta", "accuracy": 0.7269999980926514}], [{"topology": [{"type": "dense", "act": "relu", "units": 730}], "epoch": 6, "batch_size": 64, "loss": "binary_crossentropy", "opt": "adagrad", "accuracy": 0.07270000874996185}, {"topology": [{"type": "dense", "act": "relu", "units": 730}], "epoch": 7, "batch_size": 64, "loss": "mean_absolute_error", "opt": "nadam", "accuracy": 0.1860000044107437}, {"topology": [{"type": "dense", "act": "relu", "units": 730}], "epoch": 6, "batch_size": 64, "loss": "mean_absolute_error", "opt": "nadam", "accuracy": 0.22699999809265137}, {"topology": [{"type": "dense", "act": "relu", "units": 730}], "epoch": 5, "batch_size": 64, "loss": "binary_crossentropy", "opt": "adagrad", "accuracy": 0.028800003230571747}], [{"topology": [{"type": "dense", "act": "relu", "units": 730}], "epoch": 6, "batch_size": 64, "loss": "mean_absolute_error", "opt": "nadam", "accuracy": 0.7850000262260437}, {"topology": [{"type": "dense", "act": "relu", "units": 730}], "epoch": 5, "batch_size": 64, "loss": "categorical_crossentropy", "opt": "sgd", "accuracy": 0.6159999966621399}, {"topology": [{"type": "dense", "act": "relu", "units": 730}], "epoch": 21, "batch_size": 64, "loss": "binary_crossentropy", "opt": "adamax", "accuracy": 0.9751001000404358}, {"topology": [{"type": "dense", "act": "relu", "units": 730}], "epoch": 5, "batch_size": 64, "loss": "binary_crossentropy", "opt": "adagrad", "accuracy": 0.9686999320983887}, {"topology": [{"type": "dense", "act": "relu", "units": 730}], "epoch": 5, "batch_size": 64, "loss": "mean_squared_error", "opt": "nadam", "accuracy": 0.8619999885559082}], [{"topology": [{"type": "dense", "act": "relu", "units": 730}], "epoch": 21, "batch_size": 64, "loss": "binary_crossentropy", "opt": "adamax", "accuracy": 0.9740000367164612}, {"topology": [{"type": "dense", "act": "relu", "units": 730}], "epoch": 5, "batch_size": 64, "loss": "binary_crossentropy", "opt": "adagrad", "accuracy": 0.07120000571012497}, {"topology": [{"type": "dense", "act": "relu", "units": 730}], "epoch": 8, "batch_size": 64, "loss": "mean_squared_error", "opt": "adadelta", "accuracy": 0.8109999895095825}, {"topology": [{"type": "dense", "act": "relu", "units": 730}], "epoch": 16, "batch_size": 64, "loss": "mean_absolute_error", "opt": "adadelta", "accuracy": 0.8199999928474426}], [{"topology": [{"type": "dense", "act": "relu", "units": 730}], "epoch": 21, "batch_size": 64, "loss": "binary_crossentropy", "opt": "adamax", "accuracy": 0.23809999227523804}, {"topology": [{"type": "dense", "act": "relu", "units": 730}], "epoch": 20, "batch_size": 64, "loss": "binary_crossentropy", "opt": "adamax", "accuracy": 0.972000002861023}, {"topology": [{"type": "dense", "act": "relu", "units": 730}], "epoch": 20, "batch_size": 64, "loss": "mean_absolute_error", "opt": "nadam", "accuracy": 0.32899999618530273}, {"topology": [{"type": "dense", "act": "relu", "units": 730}], "epoch": 20, "batch_size": 64, "loss": "mean_absolute_error", "opt": "adam", "accuracy": 0.08500000089406967}, {"topology": [{"type": "dense", "act": "relu", "units": 730}], "epoch": 20, "batch_size": 64, "loss": "sparse_categorical_crossentropy", "opt": "adadelta", "accuracy": 0}], [{"topology": [{"type": "dense", "act": "relu", "units": 730}], "epoch": 20, "batch_size": 64, "loss": "binary_crossentropy", "opt": "adamax", "accuracy": 0.9718999266624451}, {"topology": [{"type": "dense", "act": "relu", "units": 730}], "epoch": 68, "batch_size": 64, "loss": "mean_absolute_error", "opt": "nadam", "accuracy": 0.30000001192092896}, {"topology": [{"type": "dense", "act": "relu", "units": 730}], "epoch": 75, "batch_size": 64, "loss": "sparse_categorical_crossentropy", "opt": "rmsprop", "accuracy": 0}, {"topology": [{"type": "dense", "act": "relu", "units": 730}], "epoch": 20, "batch_size": 64, "loss": "binary_crossentropy", "opt": "sgd", "accuracy": 0.8063998818397522}], [{"topology": [{"type": "dense", "act": "relu", "units": 730}], "epoch": 20, "batch_size": 64, "loss": "binary_crossentropy", "opt": "adamax", "accuracy": 0.9246999621391296}, {"topology": [{"type": "dense", "act": "relu", "units": 730}], "epoch": 20, "batch_size": 64, "loss": "sparse_categorical_crossentropy", "opt": "sgd", "accuracy": 0}, {"topology": [{"type": "dense", "act": "relu", "units": 730}], "epoch": 20, "batch_size": 64, "loss": "categorical_crossentropy", "opt": "adagrad", "accuracy": 0.8759999871253967}, {"topology": [{"type": "dense", "act": "relu", "units": 730}], "epoch": 20, "batch_size": 64, "loss": "mean_squared_error", "opt": "adam", "accuracy": 0.8730000257492065}, {"topology": [{"type": "dense", "act": "relu", "units": 730}], "epoch": 20, "batch_size": 64, "loss": "categorical_crossentropy", "opt": "adadelta", "accuracy": 0.21299999952316284}], [{"topology": [{"type": "dense", "act": "relu", "units": 730}], "epoch": 20, "batch_size": 64, "loss": "binary_crossentropy", "opt": "adamax", "accuracy": 0.9720998406410217}, {"topology": [{"type": "dense", "act": "relu", "units": 730}], "epoch": 20, "batch_size": 64, "loss": "categorical_crossentropy", "opt": "adagrad", "accuracy": 0.453000009059906}, {"topology": [{"type": "dense", "act": "relu", "units": 730}], "epoch": 20, "batch_size": 64, "loss": "binary_crossentropy", "opt": "adam", "accuracy": 0.9750001430511475}, {"topology": [{"type": "dense", "act": "relu", "units": 730}], "epoch": 20, "batch_size": 64, "loss": "binary_crossentropy", "opt": "adadelta", "accuracy": 0.3117999732494354}], [{"topology": [{"type": "dense", "act": "relu", "units": 730}], "epoch": 20, "batch_size": 64, "loss": "binary_crossentropy", "opt": "adam", "accuracy": 0.9136999249458313}, {"topology": [{"type": "dense", "act": "relu", "units": 730}], "epoch": 20, "batch_size": 64, "loss": "mean_absolute_error", "opt": "nadam", "accuracy": 0.8550000190734863}, {"topology": [{"type": "dense", "act": "relu", "units": 730}], "epoch": 20, "batch_size": 64, "loss": "mean_absolute_error", "opt": "rmsprop", "accuracy": 0.289000004529953}, {"topology": [{"type": "dense", "act": "relu", "units": 730}], "epoch": 20, "batch_size": 64, "loss": "categorical_crossentropy", "opt": "rmsprop", "accuracy": 0.08500000089406967}, {"topology": [{"type": "dense", "act": "relu", "units": 730}], "epoch": 20, "batch_size": 64, "loss": "sparse_categorical_crossentropy", "opt": "rmsprop", "accuracy": 0}], [{"topology": [{"type": "dense", "act": "relu", "units": 730}], "epoch": 20, "batch_size": 64, "loss": "binary_crossentropy", "opt": "adam", "accuracy": 0.14710001647472382}, {"topology": [{"type": "dense", "act": "relu", "units": 730}], "epoch": 20, "batch_size": 64, "loss": "mean_absolute_error", "opt": "nadam", "accuracy": 0.8730000257492065}, {"topology": [{"type": "dense", "act": "relu", "units": 730}], "epoch": 20, "batch_size": 64, "loss": "categorical_crossentropy", "opt": "nadam", "accuracy": 0.08500000089406967}, {"topology": [{"type": "dense", "act": "relu", "units": 730}], "epoch": 20, "batch_size": 64, "loss": "sparse_categorical_crossentropy", "opt": "adam", "accuracy": 0}], [{"topology": [{"type": "dense", "act": "relu", "units": 730}], "epoch": 20, "batch_size": 64, "loss": "mean_absolute_error", "opt": "nadam", "accuracy": 0.8809999823570251}, {"topology": [{"type": "dense", "act": "relu", "units": 730}], "epoch": 20, "batch_size": 64, "loss": "sparse_categorical_crossentropy", "opt": "sgd", "accuracy": 0}, {"topology": [{"type": "dense", "act": "relu", "units": 730}], "epoch": 20, "batch_size": 64, "loss": "mean_squared_error", "opt": "adamax", "accuracy": 0.8629999756813049}, {"topology": [{"type": "dense", "act": "relu", "units": 730}], "epoch": 20, "batch_size": 64, "loss": "binary_crossentropy", "opt": "adadelta", "accuracy": 0.9427000284194946}, {"topology": [{"type": "dense", "act": "relu", "units": 730}], "epoch": 20, "batch_size": 64, "loss": "mean_squared_error", "opt": "sgd", "accuracy": 0.5270000100135803}], [{"topology": [{"type": "dense", "act": "relu", "units": 730}], "epoch": 20, "batch_size": 64, "loss": "binary_crossentropy", "opt": "adadelta", "accuracy": 0.43230003118515015}, {"topology": [{"type": "dense", "act": "relu", "units": 730}], "epoch": 20, "batch_size": 64, "loss": "mean_absolute_error", "opt": "nadam", "accuracy": 0.8679999709129333}, {"topology": [{"type": "dense", "act": "relu", "units": 730}], "epoch": 20, "batch_size": 64, "loss": "mean_absolute_error", "opt": "adadelta", "accuracy": 0.8479999899864197}, {"topology": [{"type": "dense", "act": "relu", "units": 730}], "epoch": 20, "batch_size": 64, "loss": "mean_absolute_error", "opt": "nadam", "accuracy": 0.35100001096725464}], [{"topology": [{"type": "dense", "act": "relu", "units": 730}], "epoch": 20, "batch_size": 64, "loss": "mean_absolute_error", "opt": "nadam", "accuracy": 0.8709999918937683}, {"topology": [{"type": "dense", "act": "relu", "units": 730}], "epoch": 20, "batch_size": 64, "loss": "sparse_categorical_crossentropy", "opt": "adamax", "accuracy": 0}, {"topology": [{"type": "dense", "act": "relu", "units": 730}], "epoch": 20, "batch_size": 64, "loss": "binary_crossentropy", "opt": "adam", "accuracy": 0.9398999810218811}, {"topology": [{"type": "dense", "act": "relu", "units": 730}], "epoch": 20, "batch_size": 64, "loss": "categorical_crossentropy", "opt": "nadam", "accuracy": 0.1679999977350235}, {"topology": [{"type": "dense", "act": "relu", "units": 730}], "epoch": 20, "batch_size": 64, "loss": "mean_absolute_error", "opt": "adagrad", "accuracy": 0.37700000405311584}], [{"topology": [{"type": "dense", "act": "relu", "units": 730}], "epoch": 20, "batch_size": 64, "loss": "binary_crossentropy", "opt": "adam", "accuracy": 0.22470001876354218}, {"topology": [{"type": "dense", "act": "relu", "units": 730}], "epoch": 20, "batch_size": 64, "loss": "mean_absolute_error", "opt": "nadam", "accuracy": 0.8610000014305115}, {"topology": [{"type": "dense", "act": "relu", "units": 730}], "epoch": 20, "batch_size": 64, "loss": "mean_squared_error", "opt": "adadelta", "accuracy": 0.859000027179718}, {"topology": [{"type": "dense", "act": "relu", "units": 730}], "epoch": 20, "batch_size": 64, "loss": "mean_absolute_error", "opt": "adadelta", "accuracy": 0.17800000309944153}], [{"topology": [{"type": "dense", "act": "relu", "units": 730}], "epoch": 20, "batch_size": 64, "loss": "mean_absolute_error", "opt": "nadam", "accuracy": 0.878000020980835}, {"topology": [{"type": "dense", "act": "relu", "units": 730}], "epoch": 20, "batch_size": 64, "loss": "categorical_crossentropy", "opt": "adagrad", "accuracy": 0.8679999709129333}, {"topology": [{"type": "dense", "act": "relu", "units": 730}], "epoch": 20, "batch_size": 64, "loss": "categorical_crossentropy", "opt": "adagrad", "accuracy": 0.3840000033378601}, {"topology": [{"type": "dense", "act": "relu", "units": 730}], "epoch": 20, "batch_size": 64, "loss": "sparse_categorical_crossentropy", "opt": "adam", "accuracy": 0}, {"topology": [{"type": "dense", "act": "relu", "units": 730}], "epoch": 20, "batch_size": 64, "loss": "mean_squared_error", "opt": "rmsprop", "accuracy": 0.8849999904632568}], [{"topology": [{"type": "dense", "act": "relu", "units": 730}], "epoch": 20, "batch_size": 64, "loss": "mean_squared_error", "opt": "rmsprop", "accuracy": 0.8949999809265137}, {"topology": [{"type": "dense", "act": "relu", "units": 730}], "epoch": 20, "batch_size": 64, "loss": "mean_absolute_error", "opt": "nadam", "accuracy": 0.8600000143051147}, {"topology": [{"type": "dense", "act": "relu", "units": 730}], "epoch": 20, "batch_size": 64, "loss": "sparse_categorical_crossentropy", "opt": "adam", "accuracy": 0}, {"topology": [{"type": "dense", "act": "relu", "units": 730}], "epoch": 20, "batch_size": 64, "loss": "mean_squared_error", "opt": "rmsprop", "accuracy": 0.8859999775886536}], [{"topology": [{"type": "dense", "act": "relu", "units": 730}], "epoch": 20, "batch_size": 64, "loss": "mean_squared_error", "opt": "rmsprop", "accuracy": 0.5929999947547913}, {"topology": [{"type": "dense", "act": "relu", "units": 730}], "epoch": 20, "batch_size": 64, "loss": "mean_squared_error", "opt": "adam", "accuracy": 0.5400000214576721}, {"topology": [{"type": "dense", "act": "relu", "units": 730}], "epoch": 20, "batch_size": 64, "loss": "mean_absolute_error", "opt": "adagrad", "accuracy": 0.6679999828338623}, {"topology": [{"type": "dense", "act": "relu", "units": 730}], "epoch": 20, "batch_size": 64, "loss": "binary_crossentropy", "opt": "adamax", "accuracy": 0.2760999798774719}, {"topology": [{"type": "dense", "act": "relu", "units": 730}], "epoch": 20, "batch_size": 64, "loss": "mean_absolute_error", "opt": "sgd", "accuracy": 0.1770000010728836}], [{"topology": [{"type": "dense", "act": "relu", "units": 730}], "epoch": 20, "batch_size": 64, "loss": "mean_absolute_error", "opt": "adagrad", "accuracy": 0.28700000047683716}, {"topology": [{"type": "dense", "act": "relu", "units": 730}], "epoch": 20, "batch_size": 64, "loss": "mean_squared_error", "opt": "rmsprop", "accuracy": 0.8989999890327454}, {"topology": [{"type": "dense", "act": "relu", "units": 730}], "epoch": 20, "batch_size": 64, "loss": "sparse_categorical_crossentropy", "opt": "nadam", "accuracy": 0}, {"topology": [{"type": "dense", "act": "relu", "units": 730}], "epoch": 20, "batch_size": 64, "loss": "sparse_categorical_crossentropy", "opt": "adagrad", "accuracy": 0}], [{"topology": [{"type": "dense", "act": "relu", "units": 730}], "epoch": 20, "batch_size": 64, "loss": "mean_squared_error", "opt": "rmsprop", "accuracy": 0.8939999938011169}, {"topology": [{"type": "dense", "act": "relu", "units": 730}], "epoch": 20, "batch_size": 64, "loss": "mean_squared_error", "opt": "adamax", "accuracy": 0.875}, {"topology": [{"type": "dense", "act": "relu", "units": 730}], "epoch": 20, "batch_size": 64, "loss": "binary_crossentropy", "opt": "sgd", "accuracy": 0.899999737739563}, {"topology": [{"type": "dense", "act": "relu", "units": 730}], "epoch": 20, "batch_size": 64, "loss": "categorical_crossentropy", "opt": "sgd", "accuracy": 0.12600000202655792}, {"topology": [{"type": "dense", "act": "relu", "units": 730}], "epoch": 54, "batch_size": 64, "loss": "mean_absolute_error", "opt": "sgd", "accuracy": 0.5899999737739563}], [{"topology": [{"type": "dense", "act": "relu", "units": 730}], "epoch": 20, "batch_size": 64, "loss": "binary_crossentropy", "opt": "sgd", "accuracy": 0.003999999724328518}, {"topology": [{"type": "dense", "act": "relu", "units": 730}], "epoch": 20, "batch_size": 64, "loss": "mean_squared_error", "opt": "rmsprop", "accuracy": 0.8659999966621399}, {"topology": [{"type": "dense", "act": "relu", "units": 730}], "epoch": 20, "batch_size": 64, "loss": "categorical_crossentropy", "opt": "adadelta", "accuracy": 0.8529999852180481}, {"topology": [{"type": "dense", "act": "relu", "units": 730}], "epoch": 107, "batch_size": 64, "loss": "binary_crossentropy", "opt": "adam", "accuracy": 0.9354000687599182}], [{"topology": [{"type": "dense", "act": "relu", "units": 730}], "epoch": 107, "batch_size": 64, "loss": "binary_crossentropy", "opt": "adam", "accuracy": 0.9223000407218933}, {"topology": [{"type": "dense", "act": "relu", "units": 730}], "epoch": 106, "batch_size": 64, "loss": "mean_squared_error", "opt": "nadam", "accuracy": 0.8999999761581421}, {"topology": [{"type": "dense", "act": "relu", "units": 730}], "epoch": 106, "batch_size": 64, "loss": "sparse_categorical_crossentropy", "opt": "adam", "accuracy": 0}, {"topology": [{"type": "dense", "act": "relu", "units": 730}], "epoch": 106, "batch_size": 64, "loss": "mean_squared_error", "opt": "adadelta", "accuracy": 0.871999979019165}, {"topology": [{"type": "dense", "act": "relu", "units": 730}], "epoch": 106, "batch_size": 64, "loss": "categorical_crossentropy", "opt": "adagrad", "accuracy": 0.2029999941587448}], [{"topology": [{"type": "dense", "act": "relu", "units": 730}], "epoch": 107, "batch_size": 64, "loss": "binary_crossentropy", "opt": "adam", "accuracy": 0.9764999747276306}, {"topology": [{"type": "dense", "act": "relu", "units": 730}], "epoch": 106, "batch_size": 64, "loss": "mean_squared_error", "opt": "nadam", "accuracy": 0.902999997138977}, {"topology": [{"type": "dense", "act": "relu", "units": 730}], "epoch": 105, "batch_size": 64, "loss": "categorical_crossentropy", "opt": "adamax", "accuracy": 0.13099999725818634}, {"topology": [{"type": "dense", "act": "relu", "units": 730}], "epoch": 106, "batch_size": 64, "loss": "sparse_categorical_crossentropy", "opt": "nadam", "accuracy": 0}], [{"topology": [{"type": "dense", "act": "relu", "units": 730}], "epoch": 107, "batch_size": 64, "loss": "binary_crossentropy", "opt": "adam", "accuracy": 0.9735998511314392}, {"topology": [{"type": "dense", "act": "relu", "units": 730}], "epoch": 106, "batch_size": 64, "loss": "mean_squared_error", "opt": "adagrad", "accuracy": 0.8790000081062317}, {"topology": [{"type": "dense", "act": "relu", "units": 730}], "epoch": 138, "batch_size": 64, "loss": "mean_squared_error", "opt": "sgd", "accuracy": 0.609000027179718}, {"topology": [{"type": "dense", "act": "relu", "units": 730}], "epoch": 106, "batch_size": 64, "loss": "binary_crossentropy", "opt": "adadelta", "accuracy": 0.9455999732017517}, {"topology": [{"type": "dense", "act": "relu", "units": 730}], "epoch": 106, "batch_size": 64, "loss": "mean_absolute_error", "opt": "adam", "accuracy": 0.9049999713897705}], [{"topology": [{"type": "dense", "act": "relu", "units": 730}], "epoch": 107, "batch_size": 64, "loss": "binary_crossentropy", "opt": "adam", "accuracy": 0.9231001138687134}, {"topology": [{"type": "dense", "act": "relu", "units": 730}], "epoch": 106, "batch_size": 64, "loss": "binary_crossentropy", "opt": "adadelta", "accuracy": 0.9721999764442444}, {"topology": [{"type": "dense", "act": "relu", "units": 730}], "epoch": 106, "batch_size": 64, "loss": "categorical_crossentropy", "opt": "adam", "accuracy": 0.08500000089406967}, {"topology": [{"type": "dense", "act": "relu", "units": 730}], "epoch": 106, "batch_size": 64, "loss": "sparse_categorical_crossentropy", "opt": "rmsprop", "accuracy": 0}], [{"topology": [{"type": "dense", "act": "relu", "units": 730}], "epoch": 106, "batch_size": 64, "loss": "binary_crossentropy", "opt": "adadelta", "accuracy": 0.2986999452114105}, {"topology": [{"type": "dense", "act": "relu", "units": 730}], "epoch": 105, "batch_size": 64, "loss": "sparse_categorical_crossentropy", "opt": "adadelta", "accuracy": 0}, {"topology": [{"type": "dense", "act": "relu", "units": 730}], "epoch": 105, "batch_size": 64, "loss": "mean_squared_error", "opt": "adagrad", "accuracy": 0.08500000089406967}, {"topology": [{"type": "dense", "act": "relu", "units": 730}], "epoch": 105, "batch_size": 64, "loss": "sparse_categorical_crossentropy", "opt": "adam", "accuracy": 0}, {"topology": [{"type": "dense", "act": "relu", "units": 730}], "epoch": 105, "batch_size": 64, "loss": "categorical_crossentropy", "opt": "nadam", "accuracy": 0.08500000089406967}], [{"topology": [{"type": "dense", "act": "relu", "units": 730}], "epoch": 106, "batch_size": 64, "loss": "binary_crossentropy", "opt": "adadelta", "accuracy": 0.937700092792511}, {"topology": [{"type": "dense", "act": "relu", "units": 730}], "epoch": 105, "batch_size": 64, "loss": "mean_squared_error", "opt": "adagrad", "accuracy": 0.878000020980835}, {"topology": [{"type": "dense", "act": "relu", "units": 730}], "epoch": 105, "batch_size": 64, "loss": "binary_crossentropy", "opt": "sgd", "accuracy": 0.921299934387207}, {"topology": [{"type": "dense", "act": "relu", "units": 730}], "epoch": 104, "batch_size": 64, "loss": "categorical_crossentropy", "opt": "nadam", "accuracy": 0.878000020980835}], [{"topology": [{"type": "dense", "act": "relu", "units": 730}], "epoch": 106, "batch_size": 64, "loss": "binary_crossentropy", "opt": "adadelta", "accuracy": 0.4177999794483185}, {"topology": [{"type": "dense", "act": "relu", "units": 730}], "epoch": 105, "batch_size": 64, "loss": "mean_absolute_error", "opt": "adadelta", "accuracy": 0.8999999761581421}, {"topology": [{"type": "dense", "act": "relu", "units": 730}], "epoch": 105, "batch_size": 64, "loss": "categorical_crossentropy", "opt": "rmsprop", "accuracy": 0.08500000089406967}, {"topology": [{"type": "dense", "act": "relu", "units": 730}], "epoch": 105, "batch_size": 64, "loss": "mean_squared_error", "opt": "rmsprop", "accuracy": 0.9010000228881836}, {"topology": [{"type": "dense", "act": "relu", "units": 730}], "epoch": 105, "batch_size": 64, "loss": "sparse_categorical_crossentropy", "opt": "adam", "accuracy": 0}], [{"topology": [{"type": "dense", "act": "relu", "units": 730}], "epoch": 105, "batch_size": 64, "loss": "mean_squared_error", "opt": "rmsprop", "accuracy": 0.902999997138977}, {"topology": [{"type": "dense", "act": "relu", "units": 730}], "epoch": 105, "batch_size": 64, "loss": "mean_absolute_error", "opt": "adadelta", "accuracy": 0.8579999804496765}, {"topology": [{"type": "dense", "act": "relu", "units": 730}], "epoch": 104, "batch_size": 64, "loss": "mean_squared_error", "opt": "adadelta", "accuracy": 0.7419999837875366}, {"topology": [{"type": "dense", "act": "relu", "units": 730}], "epoch": 152, "batch_size": 64, "loss": "binary_crossentropy", "opt": "adamax", "accuracy": 0.2361999899148941}], [{"topology": [{"type": "dense", "act": "relu", "units": 730}], "epoch": 105, "batch_size": 64, "loss": "mean_squared_error", "opt": "rmsprop", "accuracy": 0.878000020980835}, {"topology": [{"type": "dense", "act": "relu", "units": 730}], "epoch": 104, "batch_size": 64, "loss": "categorical_crossentropy", "opt": "adadelta", "accuracy": 0.18700000643730164}, {"topology": [{"type": "dense", "act": "relu", "units": 730}], "epoch": 104, "batch_size": 64, "loss": "sparse_categorical_crossentropy", "opt": "adagrad", "accuracy": 0}, {"topology": [{"type": "dense", "act": "relu", "units": 730}], "epoch": 104, "batch_size": 64, "loss": "mean_squared_error", "opt": "adamax", "accuracy": 0.8889999985694885}, {"topology": [{"type": "dense", "act": "relu", "units": 730}], "epoch": 104, "batch_size": 64, "loss": "mean_absolute_error", "opt": "rmsprop", "accuracy": 0.21199999749660492}], [{"topology": [{"type": "dense", "act": "relu", "units": 730}], "epoch": 104, "batch_size": 64, "loss": "mean_squared_error", "opt": "adamax", "accuracy": 0.8769999742507935}, {"topology": [{"type": "dense", "act": "relu", "units": 730}], "epoch": 105, "batch_size": 64, "loss": "mean_squared_error", "opt": "rmsprop", "accuracy": 0.8989999890327454}, {"topology": [{"type": "dense", "act": "relu", "units": 730}], "epoch": 104, "batch_size": 64, "loss": "binary_crossentropy", "opt": "adadelta", "accuracy": 0.1754000037908554}, {"topology": [{"type": "dense", "act": "relu", "units": 730}], "epoch": 104, "batch_size": 64, "loss": "mean_absolute_error", "opt": "rmsprop", "accuracy": 0.8640000224113464}], [{"topology": [{"type": "dense", "act": "relu", "units": 730}], "epoch": 105, "batch_size": 64, "loss": "mean_squared_error", "opt": "rmsprop", "accuracy": 0.8759999871253967}, {"topology": [{"type": "dense", "act": "relu", "units": 730}], "epoch": 104, "batch_size": 64, "loss": "mean_absolute_error", "opt": "rmsprop", "accuracy": 0.8949999809265137}, {"topology": [{"type": "dense", "act": "relu", "units": 730}], "epoch": 104, "batch_size": 64, "loss": "mean_squared_error", "opt": "nadam", "accuracy": 0.08500000089406967}, {"topology": [{"type": "dense", "act": "relu", "units": 730}], "epoch": 104, "batch_size": 64, "loss": "mean_absolute_error", "opt": "rmsprop", "accuracy": 0.890999972820282}, {"topology": [{"type": "dense", "act": "relu", "units": 730}], "epoch": 104, "batch_size": 64, "loss": "binary_crossentropy", "opt": "adamax", "accuracy": 0.1307000070810318}], [{"topology": [{"type": "dense", "act": "relu", "units": 730}], "epoch": 104, "batch_size": 64, "loss": "mean_absolute_error", "opt": "rmsprop", "accuracy": 0.5419999957084656}, {"topology": [{"type": "dense", "act": "relu", "units": 730}], "epoch": 104, "batch_size": 64, "loss": "mean_absolute_error", "opt": "rmsprop", "accuracy": 0.8669999837875366}, {"topology": [{"type": "dense", "act": "relu", "units": 730}], "epoch": 104, "batch_size": 64, "loss": "binary_crossentropy", "opt": "adadelta", "accuracy": 0.25130000710487366}, {"topology": [{"type": "dense", "act": "relu", "units": 730}], "epoch": 104, "batch_size": 64, "loss": "sparse_categorical_crossentropy", "opt": "adamax", "accuracy": 0}], [{"topology": [{"type": "dense", "act": "relu", "units": 730}], "epoch": 104, "batch_size": 64, "loss": "mean_absolute_error", "opt": "rmsprop", "accuracy": 0.30300000309944153}, {"topology": [{"type": "dense", "act": "relu", "units": 730}], "epoch": 144, "batch_size": 64, "loss": "binary_crossentropy", "opt": "rmsprop", "accuracy": 0.07079999148845673}, {"topology": [{"type": "dense", "act": "relu", "units": 730}], "epoch": 104, "batch_size": 64, "loss": "categorical_crossentropy", "opt": "adagrad", "accuracy": 0.33399999141693115}, {"topology": [{"type": "dense", "act": "relu", "units": 730}], "epoch": 104, "batch_size": 64, "loss": "mean_squared_error", "opt": "adadelta", "accuracy": 0.8920000195503235}, {"topology": [{"type": "dense", "act": "relu", "units": 730}], "epoch": 104, "batch_size": 64, "loss": "mean_absolute_error", "opt": "adagrad", "accuracy": 0.08500000089406967}], [{"topology": [{"type": "dense", "act": "relu", "units": 730}], "epoch": 104, "batch_size": 64, "loss": "mean_squared_error", "opt": "adadelta", "accuracy": 0.8790000081062317}, {"topology": [{"type": "dense", "act": "relu", "units": 730}], "epoch": 104, "batch_size": 64, "loss": "categorical_crossentropy", "opt": "adagrad", "accuracy": 0.8730000257492065}, {"topology": [{"type": "dense", "act": "relu", "units": 730}], "epoch": 104, "batch_size": 64, "loss": "sparse_categorical_crossentropy", "opt": "adamax", "accuracy": 0}, {"topology": [{"type": "dense", "act": "relu", "units": 730}], "epoch": 104, "batch_size": 64, "loss": "mean_squared_error", "opt": "rmsprop", "accuracy": 0.8130000233650208}], [{"topology": [{"type": "dense", "act": "relu", "units": 730}], "epoch": 104, "batch_size": 64, "loss": "mean_squared_error", "opt": "adadelta", "accuracy": 0.8600000143051147}, {"topology": [{"type": "dense", "act": "relu", "units": 730}], "epoch": 104, "batch_size": 64, "loss": "sparse_categorical_crossentropy", "opt": "sgd", "accuracy": 0}, {"topology": [{"type": "dense", "act": "relu", "units": 730}], "epoch": 104, "batch_size": 64, "loss": "categorical_crossentropy", "opt": "sgd", "accuracy": 0.8429999947547913}, {"topology": [{"type": "dense", "act": "relu", "units": 730}], "epoch": 190, "batch_size": 64, "loss": "sparse_categorical_crossentropy", "opt": "rmsprop", "accuracy": 0}, {"topology": [{"type": "dense", "act": "relu", "units": 730}], "epoch": 104, "batch_size": 64, "loss": "sparse_categorical_crossentropy", "opt": "rmsprop", "accuracy": 0}], [{"topology": [{"type": "dense", "act": "relu", "units": 730}], "epoch": 104, "batch_size": 64, "loss": "mean_squared_error", "opt": "adadelta", "accuracy": 0.8899999856948853}, {"topology": [{"type": "dense", "act": "relu", "units": 730}], "epoch": 104, "batch_size": 64, "loss": "categorical_crossentropy", "opt": "sgd", "accuracy": 0.08500000089406967}, {"topology": [{"type": "dense", "act": "relu", "units": 730}], "epoch": 104, "batch_size": 64, "loss": "binary_crossentropy", "opt": "sgd", "accuracy": 0.6064000129699707}, {"topology": [{"type": "dense", "act": "relu", "units": 730}], "epoch": 104, "batch_size": 64, "loss": "sparse_categorical_crossentropy", "opt": "adamax", "accuracy": 0}], [{"topology": [{"type": "dense", "act": "relu", "units": 730}], "epoch": 104, "batch_size": 64, "loss": "mean_squared_error", "opt": "adadelta", "accuracy": 0.8840000033378601}, {"topology": [{"type": "dense", "act": "relu", "units": 730}], "epoch": 104, "batch_size": 64, "loss": "sparse_categorical_crossentropy", "opt": "adagrad", "accuracy": 0}, {"topology": [{"type": "dense", "act": "relu", "units": 730}], "epoch": 104, "batch_size": 64, "loss": "mean_squared_error", "opt": "adadelta", "accuracy": 0.8659999966621399}, {"topology": [{"type": "dense", "act": "relu", "units": 730}], "epoch": 104, "batch_size": 64, "loss": "categorical_crossentropy", "opt": "adadelta", "accuracy": 0.17900000512599945}, {"topology": [{"type": "dense", "act": "relu", "units": 730}], "epoch": 104, "batch_size": 64, "loss": "categorical_crossentropy", "opt": "adam", "accuracy": 0.10999999940395355}], [{"topology": [{"type": "dense", "act": "relu", "units": 730}], "epoch": 104, "batch_size": 64, "loss": "mean_squared_error", "opt": "adadelta", "accuracy": 0.8600000143051147}, {"topology": [{"type": "dense", "act": "relu", "units": 730}], "epoch": 104, "batch_size": 64, "loss": "mean_squared_error", "opt": "adadelta", "accuracy": 0.8619999885559082}, {"topology": [{"type": "dense", "act": "relu", "units": 730}], "epoch": 104, "batch_size": 64, "loss": "mean_squared_error", "opt": "adamax", "accuracy": 0.8849999904632568}, {"topology": [{"type": "dense", "act": "relu", "units": 730}], "epoch": 104, "batch_size": 64, "loss": "mean_absolute_error", "opt": "adam", "accuracy": 0.8930000066757202}]]